openctr/__init__.py
openctr/autotuner.py
openctr/features.py
openctr/metrics.py
openctr/preprocess.py
openctr/utils.py
openctr/datasets/__init__.py
openctr/datasets/avazu.py
openctr/datasets/criteo.py
openctr/datasets/data_utils.py
openctr/datasets/movielens1m.py
openctr/datasets/tencent.py
openctr/pytorch/__init__.py
openctr/pytorch/data_generator.py
openctr/pytorch/utils.py
openctr/pytorch/layers/__init__.py
openctr/pytorch/layers/attention.py
openctr/pytorch/layers/deep.py
openctr/pytorch/layers/embedding.py
openctr/pytorch/layers/sequence.py
openctr/pytorch/layers/shallow.py
openctr/pytorch/models/DCN.py
openctr/pytorch/models/DNN.py
openctr/pytorch/models/DeepFM.py
openctr/pytorch/models/FM.py
openctr/pytorch/models/LR.py
openctr/pytorch/models/WideDeep.py
openctr/pytorch/models/__init__.py
openctr/pytorch/models/base_model.py
openctr/pytorch/models/xDeepFM.py
openctr/tensorflow/__init__.py
openctr/tensorflow/callbacks.py
openctr/tensorflow/data_generator.py
openctr/tensorflow/utils.py
openctr/tensorflow/layers/__init__.py
openctr/tensorflow/layers/core.py
openctr/tensorflow/layers/dense_layer.py
openctr/tensorflow/layers/linear_layer.py
openctr/tensorflow/layers/sequence_encoder.py
openctr/tensorflow/models/DNN.py
openctr/tensorflow/models/DeepFM.py
openctr/tensorflow/models/FM.py
openctr/tensorflow/models/LR.py
openctr/tensorflow/models/WideDeep.py
openctr/tensorflow/models/__init__.py
openctr/tensorflow/models/base_model.py
openctr-0.1.0.dist-info/METADATA
openctr-0.1.0.dist-info/RECORD
openctr-0.1.0.dist-info/WHEEL
openctr-0.1.0.dist-info/top_level.txt
