Metadata-Version: 2.1
Name: openctr
Version: 0.1.0
Summary: A configurable, tunable, and reproducible library for CTR prediction
Home-page: https://github.com/xue-pai/OpenCTR
Author: xpai
Author-email: info@logpai.com
License: Apache License 2
Download-URL: https://github.com/xue-pai/OpenCTR
Keywords: ctr prediction,recommender systems,ctr,cvr,pytorch
Platform: UNKNOWN
Classifier: License :: OSI Approved :: Apache Software License
Classifier: Operating System :: OS Independent
Classifier: Intended Audience :: Developers
Classifier: Intended Audience :: Education
Classifier: Intended Audience :: Science/Research
Classifier: Programming Language :: Python :: 3
Classifier: Programming Language :: Python :: 3.6
Classifier: Topic :: Scientific/Engineering
Classifier: Topic :: Scientific/Engineering :: Artificial Intelligence
Classifier: Topic :: Software Development
Classifier: Topic :: Software Development :: Libraries
Classifier: Topic :: Software Development :: Libraries :: Python Modules
Requires-Python: ==3.6.*
Provides-Extra: cpu
Provides-Extra: gpu
Requires-Dist: pandas
Requires-Dist: numpy
Requires-Dist: h5py
Requires-Dist: PyYAML
Provides-Extra: cpu
Requires-Dist: torch (==1.0.*); extra == 'cpu'
Provides-Extra: gpu
Requires-Dist: torch (==1.0.*); extra == 'gpu'
